LICENSE
LICENSE_cctorch
LICENSE_groundingdino
LICENSE_sam2
MANIFEST.in
README.md
pyproject.toml
setup.py
grounding_dino/docker_test.py
grounding_dino/environment.yaml
grounding_dino/setup.py
grounding_dino/demo/create_coco_dataset.py
grounding_dino/demo/gradio_app.py
grounding_dino/demo/inference_on_a_image.py
grounding_dino/demo/test_ap_on_coco.py
grounding_dino/groundingdino/__init__.py
grounding_dino/groundingdino/version.py
grounding_dino/groundingdino/config/GroundingDINO_SwinB_cfg.py
grounding_dino/groundingdino/config/GroundingDINO_SwinT_OGC.py
grounding_dino/groundingdino/config/__init__.py
grounding_dino/groundingdino/datasets/__init__.py
grounding_dino/groundingdino/datasets/cocogrounding_eval.py
grounding_dino/groundingdino/datasets/transforms.py
grounding_dino/groundingdino/models/__init__.py
grounding_dino/groundingdino/models/registry.py
grounding_dino/groundingdino/models/GroundingDINO/__init__.py
grounding_dino/groundingdino/models/GroundingDINO/bertwarper.py
grounding_dino/groundingdino/models/GroundingDINO/fuse_modules.py
grounding_dino/groundingdino/models/GroundingDINO/groundingdino.py
grounding_dino/groundingdino/models/GroundingDINO/ms_deform_attn.py
grounding_dino/groundingdino/models/GroundingDINO/transformer.py
grounding_dino/groundingdino/models/GroundingDINO/transformer_vanilla.py
grounding_dino/groundingdino/models/GroundingDINO/utils.py
grounding_dino/groundingdino/models/GroundingDINO/backbone/__init__.py
grounding_dino/groundingdino/models/GroundingDINO/backbone/backbone.py
grounding_dino/groundingdino/models/GroundingDINO/backbone/position_encoding.py
grounding_dino/groundingdino/models/GroundingDINO/backbone/swin_transformer.py
grounding_dino/groundingdino/util/__init__.py
grounding_dino/groundingdino/util/box_ops.py
grounding_dino/groundingdino/util/get_tokenlizer.py
grounding_dino/groundingdino/util/inference.py
grounding_dino/groundingdino/util/logger.py
grounding_dino/groundingdino/util/misc.py
rai_gsam2.egg-info/PKG-INFO
rai_gsam2.egg-info/SOURCES.txt
rai_gsam2.egg-info/dependency_links.txt
rai_gsam2.egg-info/requires.txt
rai_gsam2.egg-info/top_level.txt
