Metadata-Version: 2.4
Name: rai-gsam2
Version: 1.1.3
Summary: Grounded SAM 2: Ground and Track Anything in Videos (RobotecAI fork)
Home-page: https://github.com/facebookresearch/sam2
Author: Meta AI
Author-email: Meta AI <segment-anything@meta.com>, Maciej Majek <maciej.majek@robotec.ai>, Bartłomiej Boczek <bartlomiej.boczek@robotec.ai>, Julia Jia <juliajster@gmail.com>
License: Apache-2.0
Project-URL: Homepage, https://github.com/RobotecAI/Grounded-SAM-2
Project-URL: Original, https://github.com/IDEA-Research/Grounded-SAM-2
Requires-Python: >=3.10.0
License-File: LICENSE
License-File: LICENSE_cctorch
License-File: LICENSE_groundingdino
License-File: LICENSE_sam2
Requires-Dist: torch>=2.3.1
Requires-Dist: torchvision>=0.18.1
Requires-Dist: numpy>=1.24.4
Requires-Dist: tqdm>=4.66.1
Requires-Dist: hydra-core>=1.3.2
Requires-Dist: iopath>=0.1.10
Requires-Dist: pillow>=9.4.0
Requires-Dist: opencv-python
Requires-Dist: supervision
Requires-Dist: transformers
Requires-Dist: timm
Dynamic: author
Dynamic: home-page
Dynamic: license-file
Dynamic: requires-python
